{"type":"PR","pr":{"number":19,"head":"d73c0f9e03724ecd0fdf1f6ebb84b7381b4cdf16"},"user":"gareths","status":"draft","branch":"cms/index","collection":"pages","title":"Making life easier with Workday","description":"Workday will help make life easier for Candidates, Nandocas and Managers; and will help us to make Nando’s an even better place to work.","objects":{"entry":{"path":"src/pages/index.md","sha":"d11153e91ea26161b73a53ef7d7399fd22499947"},"files":[{"path":"/static/img/family-day-heart-compass.png","sha":"8212e2b0bb570e60db76d5dce19f8663448adda2"}]},"timeStamp":"2019-08-23T08:58:09.284Z"}